Metadata-Version: 1.1
Name: emailCrawlerPY
Version: 2.0
Summary: Small tool to crawl email from given websites
Home-page: UNKNOWN
Author: Jacopin Guillaume
Author-email: guillaume.jacopin@sts-sio-caen.info
License: MIT
Keywords: scrap,scrapper,scrapping,crawl,crawler,email,mail
Platform: UNKNOWN
Classifier: Development Status :: 5 - Production/Stable
Classifier: Intended Audience :: Education
Classifier: Operating System :: Microsoft :: Windows :: Windows 10
Classifier: License :: OSI Approved :: MIT License
Classifier: Programming Language :: Python :: 3
